<?xml version="1.0" encoding="utf-8" ?><dwsync><file name="plugins.js" server="MacHD/Library/WebServer" local="3412512008" remote="12002446600" /><file name="script.js" server="MacHD/Library/WebServer" local="3417115429" remote="12007050021" /><file name="plugins.js" server="ftp.artjail.com/new/" local="3412512008" remote="12007583132" /><file name="script.js" server="ftp.artjail.com/new/" local="3418048048" remote="12007998452" /><file name="html5Preloader.js" server="ftp.artjail.com/new/" local="3414912840" remote="12007998452" /><file name="html5Preloader.js" server="50.63.83.1//new/" local="3414912840" remote="12008074652" /><file name="plugins.js" server="50.63.83.1//new/" local="3412512008" remote="12008074652" /><file name="script.js" server="50.63.83.1//new/" local="3420553277" remote="12010502252" /><file name="jquery.tinyscrollbar.min.js" server="50.63.83.1//new/" local="3418140060" remote="12008884652" /><file name="froogaloop2.min.js" server="50.63.83.1//new/" local="3419525367" remote="12009478232" /><file name="jquery.fitvids.js" server="50.63.83.1//new/" local="3420562470" remote="12010511432" /></dwsync>